{
  "version": "1",
  "data": [
    {
      "name": "&nextentry&Skparab1&rname=Shubham+Parab&nextentry&This+is+cool&rname=Shubham+Parab&nextentry&Shubham&rname=Shubham+Parab&nextentry&A+person&rname=Shubham&nextentry&SKPARAB1&rname=Shubham&nextentry&Skparab1&rname=&nextentry&sparab710&rname=shubham&nextentry&skparab1&rname=Shubham&nextentry&Skparab1+test&rname=Shubham&nextentry&skparab1&rname=Shubham&nextentry&Shubham&rname=Shubham+Parab&nextentry&Shubham&rname=Shubham&nextentry&Skparab1&rname=Shubha%2C&nextentry&Shubham&rname=shubham&nextentry&Shubham&rname=Shubham"
    },
    {
      "message": "&nextentry&hello+world&currenttime=2022/3/5 at 15:39:48&nextentry&now+records+message&currenttime=2022/3/5 at 15:56:52&nextentry&third+message&currenttime=2022/3/5 at 16:42:36&nextentry&Hello+world.+This+is+a+test+message+that+will+be+sent.+it+should+appear+in+a+few+minutes&currenttime=2022/3/5 at 17:46:54&nextentry&very+cool+new+message+notif&currenttime=2022/3/5 at 18:24:9&nextentry&it+works%21+very+cool&currenttime=2022/3/5 at 19:2:39&nextentry&amasinggg+it+works+so+nicely&currenttime=2022/3/5 at 19:6:9&nextentry&I+think+it+should+be+fixed+right+now&currenttime=2022/3/5 at 19:10:49&nextentry&Will+it+retain+colors%3F%0D%0AThis+is+cool+ngl&currenttime=2022/3/5 at 19:21:34&nextentry&will+it+retain+colors&currenttime=2022/3/5 at 19:38:44&nextentry&retain+colors+test+which+might+work&currenttime=2022/3/5 at 19:40:2&nextentry&last+time%2C+the+first+one+was+yellow&currenttime=2022/3/5 at 19:45:31&nextentry&last+time+the+one+was+red&currenttime=2022/3/5 at 19:53:29&nextentry&ok+the+first+one+was+green+last+time+so+this+one+shouldnt+be+green+i+hope+its+not&currenttime=2022/3/5 at 20:1:33&nextentry&nice+color+change+last+one+was+yellow&currenttime=2022/3/5 at 20:4:2"
    }
  ],
  "secondArray": [
    {
      "secondId": "2"
    }
  ]
}
